{"links": {"self": {"href": "data/repositories/osrf/gazebo-release/issues/7/comments/2165134.json"}, "html": {"href": "#!/osrf/gazebo-release/issues/7#comment-2165134"}}, "issue": {"links": {"self": {"href": "data/repositories/osrf/gazebo-release/issues/7.json"}}, "type": "issue", "id": 7, "repository": {"links": {"self": {"href": "data/repositories/osrf/gazebo-release.json"}, "html": {"href": "#!/osrf/gazebo-release"}, "avatar": {"href": "data/bytebucket.org/ravatar/{95a21594-633d-4752-b9d6-5be95d20150c}ts=default"}}, "type": "repository", "name": "gazebo-release", "full_name": "osrf/gazebo-release", "uuid": "{95a21594-633d-4752-b9d6-5be95d20150c}"}, "title": "Remove warnings produced during debuild and pbuilder runs"}, "content": {"raw": "A bunch of warnings were removed by 7464450 .  Ticket new ones as they're noticed.", "markup": "markdown", "html": "<p>A bunch of warnings were removed by <a href=\"#!/osrf/gazebo-release/commits/7464450\" rel=\"nofollow\" class=\"ap-connect-link\">7464450</a> .  Ticket new ones as they're noticed.</p>", "type": "rendered"}, "created_on": "2012-10-15T21:36:55.853838+00:00", "user": {"display_name": "Brian Gerkey", "uuid": "{3d8b5763-9dad-4be7-85c2-a7ab6cd49173}", "links": {"self": {"href": "https://api.bitbucket.org/2.0/users/%7B3d8b5763-9dad-4be7-85c2-a7ab6cd49173%7D"}, "html": {"href": "https://bitbucket.org/%7B3d8b5763-9dad-4be7-85c2-a7ab6cd49173%7D/"}, "avatar": {"href": "https://avatar-management--avatars.us-west-2.prod.public.atl-paas.net/557058:2e35028e-9ad8-4d6a-a3a5-275159a304a9/5fa9ec73-0fec-4860-a202-e34ae23b6a12/128"}}, "nickname": "Brian Gerkey", "type": "user", "account_id": "557058:2e35028e-9ad8-4d6a-a3a5-275159a304a9"}, "updated_on": null, "type": "issue_comment", "id": 2165134}